{
  "id": "OBJ_the_caustic_loom_crate_stack_0793",
  "label": "Stacked Crates",
  "description": "A stack of wooden crates",
  "important": false,
  "short_description": "stacked crates",
  "tags": [
    "ship"
  ],
  "entityType": "object",
  "info": {
    "purpose": "storage",
    "solid": true,
    "layer": "default",
    "isStructural": false,
    "material": null,
    "tint": null,
    "spriteConfig": {
      "spriteId": "crate_stack",
      "frame": null,
      "animationKey": null,
      "animated": false,
      "facing": "south"
    },
    "hp": null,
    "maxHp": null,
    "state": null,
    "contents": [
      "shoes",
      "longsleeve",
      "tunic",
      "leather_belt"
    ],
    "lightSource": null,
    "itemId": null,
    "plotId": null
  },
  "position": {
    "x": 960,
    "y": 544,
    "width": 64,
    "height": 64,
    "parent": "PLACE_the_caustic_loom"
  },
  "destinationPlaceId": null,
  "travelPath": null,
  "travelSegmentIndex": null,
  "relationships": [],
  "image": null,
  "faceAnchorY": null,
  "omitFromPlot": false,
  "aliases": null,
  "displayName": null,
  "interaction": {
    "typeId": "search"
  }
}
