{
  "id": "OBJ_the_quiet_angle_crate_1147",
  "label": "Crate",
  "description": "A simple wooden crate",
  "important": false,
  "short_description": "crate",
  "tags": [
    "common",
    "storage",
    "ship"
  ],
  "entityType": "object",
  "info": {
    "purpose": "storage",
    "solid": true,
    "layer": "default",
    "isStructural": false,
    "material": null,
    "tint": null,
    "spriteConfig": {
      "spriteId": "crate",
      "frame": null,
      "animationKey": null,
      "animated": false,
      "facing": "west"
    },
    "hp": null,
    "maxHp": null,
    "state": null,
    "contents": [
      "coin_pouch",
      "boots",
      "leather_belt",
      "longsleeve"
    ],
    "lightSource": null,
    "itemId": null,
    "plotId": null
  },
  "position": {
    "x": 544,
    "y": 448,
    "width": 32,
    "height": 32,
    "parent": "PLACE_the_quiet_angle"
  },
  "destinationPlaceId": null,
  "travelPath": null,
  "travelSegmentIndex": null,
  "relationships": [],
  "image": null,
  "faceAnchorY": null,
  "omitFromPlot": false,
  "aliases": null,
  "displayName": null,
  "interaction": {
    "typeId": "search"
  }
}
