{
  "id": "OBJ_the_rivetwright_shop_table_square_0208",
  "label": "Square Table",
  "description": "A Square Table",
  "important": false,
  "short_description": "square table",
  "tags": [
    "common",
    "furniture"
  ],
  "entityType": "object",
  "info": {
    "purpose": "table",
    "solid": true,
    "layer": "default",
    "isStructural": false,
    "material": null,
    "tint": null,
    "spriteConfig": {
      "spriteId": "table_square",
      "frame": null,
      "animationKey": null,
      "animated": false,
      "facing": "south"
    },
    "hp": null,
    "maxHp": null,
    "state": null,
    "contents": null,
    "lightSource": null,
    "itemId": null,
    "plotId": null
  },
  "position": {
    "x": 944,
    "y": 1024,
    "width": 96,
    "height": 96,
    "parent": "PLACE_the_rivetwright_shop"
  },
  "destinationPlaceId": null,
  "travelPath": null,
  "travelSegmentIndex": null,
  "relationships": [],
  "image": null,
  "faceAnchorY": null,
  "omitFromPlot": false,
  "aliases": null,
  "displayName": null,
  "interaction": null
}
